{
  "6": {
    "fit_time": [
      0.22631168365478516,
      0.22008132934570312,
      0.22084522247314453,
      0.22141695022583008,
      0.22442126274108887
    ],
    "score_time": [
      0.017269372940063477,
      0.017084360122680664,
      0.01697826385498047,
      0.016907453536987305,
      0.017293691635131836
    ],
    "test_r": [
      0.5967295684177176,
      0.5377622252244596,
      0.6854709395398673,
      0.6154288045369298,
      0.7133959486844982
    ],
    "test_r2": [
      0.345144344058153,
      0.2739044223436141,
      0.3222461053969151,
      0.34076278315121333,
      0.46400653607443565
    ],
    "test_rmse": [
      -6.040813573331616,
      -6.853528102563717,
      -7.606997148335863,
      -4.769620565362657,
      -5.04383651343445
    ],
    "test_mae": [
      -3.779045033400358,
      -4.032420254062293,
      -4.327158088647881,
      -3.3789682951965445,
      -3.364259215766161
    ],
    "best_params": {
      "check_inverse": true,
      "func": null,
      "inverse_func": null,
      "regressor__bootstrap": true,
      "regressor__ccp_alpha": 0.0,
      "regressor__criterion": "squared_error",
      "regressor__max_depth": null,
      "regressor__max_features": "sqrt",
      "regressor__max_leaf_nodes": null,
      "regressor__max_samples": null,
      "regressor__min_impurity_decrease": 0.0,
      "regressor__min_samples_leaf": 0.05034143452601762,
      "regressor__min_samples_split": 0.12935607325452472,
      "regressor__min_weight_fraction_leaf": 0.0,
      "regressor__monotonic_cst": null,
      "regressor__n_estimators": 276,
      "regressor__n_jobs": null,
      "regressor__oob_score": false,
      "regressor__random_state": null,
      "regressor__verbose": 0,
      "regressor__warm_start": false,
      "transformer__memory": null,
      "transformer__verbose": false,
      "transformer__y scaler__copy": true,
      "transformer__y scaler__with_mean": true,
      "transformer__y scaler__with_std": true
    }
  },
  "13": {
    "fit_time": [
      0.06893253326416016,
      0.06881237030029297,
      0.06786060333251953,
      0.06802940368652344,
      0.06406617164611816
    ],
    "score_time": [
      0.0122528076171875,
      0.015427589416503906,
      0.020853757858276367,
      0.020078420639038086,
      0.023901939392089844
    ],
    "test_r": [
      0.5964044840031517,
      0.597462176134832,
      0.5716924720162131,
      0.6725220070245173,
      0.5927684718640527
    ],
    "test_r2": [
      0.3281917360763448,
      0.330636272137128,
      0.29803966040325813,
      0.4289343390010446,
      0.300532376565777
    ],
    "test_rmse": [
      -6.215514078391284,
      -5.604027509081473,
      -6.929075594749424,
      -4.777475912100998,
      -7.307581057844404
    ],
    "test_mae": [
      -4.050610419379214,
      -3.3282151365969046,
      -3.836518330522556,
      -3.472333363226861,
      -4.399626773675211
    ],
    "best_params": {
      "check_inverse": true,
      "func": null,
      "inverse_func": null,
      "regressor__bootstrap": true,
      "regressor__ccp_alpha": 0.0,
      "regressor__criterion": "squared_error",
      "regressor__max_depth": null,
      "regressor__max_features": "sqrt",
      "regressor__max_leaf_nodes": null,
      "regressor__max_samples": null,
      "regressor__min_impurity_decrease": 0.0,
      "regressor__min_samples_leaf": 0.0506123654445674,
      "regressor__min_samples_split": 0.07197078550245575,
      "regressor__min_weight_fraction_leaf": 0.0,
      "regressor__monotonic_cst": null,
      "regressor__n_estimators": 69,
      "regressor__n_jobs": null,
      "regressor__oob_score": false,
      "regressor__random_state": null,
      "regressor__verbose": 0,
      "regressor__warm_start": false,
      "transformer__memory": null,
      "transformer__verbose": false,
      "transformer__y scaler__copy": true,
      "transformer__y scaler__with_mean": true,
      "transformer__y scaler__with_std": true
    }
  },
  "42": {
    "fit_time": [
      0.05557990074157715,
      0.05878806114196777,
      0.05547475814819336,
      0.05322909355163574,
      0.05290865898132324
    ],
    "score_time": [
      0.018030405044555664,
      0.010094642639160156,
      0.010165214538574219,
      0.01011967658996582,
      0.009864568710327148
    ],
    "test_r": [
      0.5572867006906894,
      0.7365837214716412,
      0.5360456767292661,
      0.6603281128148607,
      0.5195136814153246
    ],
    "test_r2": [
      0.22886783869509653,
      0.4638681489695633,
      0.27610481306022716,
      0.4088349503287838,
      0.26617832390878216
    ],
    "test_rmse": [
      -9.05683659230056,
      -5.112772724357634,
      -5.841791551074124,
      -5.053264734875036,
      -5.633276292569714
    ],
    "test_mae": [
      -4.965992633374703,
      -3.3364683900244683,
      -3.45599846739984,
      -3.3922686002798215,
      -4.039796618327588
    ],
    "best_params": {
      "check_inverse": true,
      "func": null,
      "inverse_func": null,
      "regressor__bootstrap": true,
      "regressor__ccp_alpha": 0.0,
      "regressor__criterion": "squared_error",
      "regressor__max_depth": null,
      "regressor__max_features": "sqrt",
      "regressor__max_leaf_nodes": null,
      "regressor__max_samples": null,
      "regressor__min_impurity_decrease": 0.0,
      "regressor__min_samples_leaf": 0.050765337173992314,
      "regressor__min_samples_split": 0.05198711695416256,
      "regressor__min_weight_fraction_leaf": 0.0,
      "regressor__monotonic_cst": null,
      "regressor__n_estimators": 52,
      "regressor__n_jobs": null,
      "regressor__oob_score": false,
      "regressor__random_state": null,
      "regressor__verbose": 0,
      "regressor__warm_start": false,
      "transformer__memory": null,
      "transformer__verbose": false,
      "transformer__y scaler__copy": true,
      "transformer__y scaler__with_mean": true,
      "transformer__y scaler__with_std": true
    }
  },
  "69": {
    "fit_time": [
      0.07902145385742188,
      0.07833147048950195,
      0.07480025291442871,
      0.0738372802734375,
      0.0773775577545166
    ],
    "score_time": [
      0.012139558792114258,
      0.012074708938598633,
      0.011091232299804688,
      0.011115312576293945,
      0.012742042541503906
    ],
    "test_r": [
      0.571455334191335,
      0.6359739505011383,
      0.6696203957101524,
      0.6342157825859117,
      0.5707223331053046
    ],
    "test_r2": [
      0.3058424381806881,
      0.38252092372320934,
      0.3691176569010831,
      0.27314467478349,
      0.29785439951678316
    ],
    "test_rmse": [
      -4.885954347430101,
      -5.489909279958868,
      -6.691291748947506,
      -7.758499472896275,
      -5.8910460838109335
    ],
    "test_mae": [
      -3.6458120321826684,
      -3.289972462800853,
      -4.241428616778503,
      -4.393059314385424,
      -3.4304879191531232
    ],
    "best_params": {
      "check_inverse": true,
      "func": null,
      "inverse_func": null,
      "regressor__bootstrap": true,
      "regressor__ccp_alpha": 0.0,
      "regressor__criterion": "squared_error",
      "regressor__max_depth": null,
      "regressor__max_features": "sqrt",
      "regressor__max_leaf_nodes": null,
      "regressor__max_samples": null,
      "regressor__min_impurity_decrease": 0.0,
      "regressor__min_samples_leaf": 0.05083277168428705,
      "regressor__min_samples_split": 0.06962633302947505,
      "regressor__min_weight_fraction_leaf": 0.0,
      "regressor__monotonic_cst": null,
      "regressor__n_estimators": 79,
      "regressor__n_jobs": null,
      "regressor__oob_score": false,
      "regressor__random_state": null,
      "regressor__verbose": 0,
      "regressor__warm_start": false,
      "transformer__memory": null,
      "transformer__verbose": false,
      "transformer__y scaler__copy": true,
      "transformer__y scaler__with_mean": true,
      "transformer__y scaler__with_std": true
    }
  },
  "420": {
    "fit_time": [
      1.5714163780212402,
      1.5532152652740479,
      1.5475118160247803,
      1.5416417121887207,
      1.5302953720092773
    ],
    "score_time": [
      0.0669560432434082,
      0.06678986549377441,
      0.06514596939086914,
      0.06438398361206055,
      0.06484079360961914
    ],
    "test_r": [
      0.6610683847039331,
      0.5587871479526767,
      0.7015813184752597,
      0.528861944816842,
      0.6991768707956904
    ],
    "test_r2": [
      0.39770566059362866,
      0.21575443704677622,
      0.438090558713192,
      0.2348526932815992,
      0.44611925369563643
    ],
    "test_rmse": [
      -4.347996548090918,
      -8.784934918184419,
      -5.444343035529587,
      -5.998325703798911,
      -5.4071743328163535
    ],
    "test_mae": [
      -3.04492127493311,
      -4.551127476857375,
      -3.4375303344861075,
      -4.353598595369999,
      -3.658817324762428
    ],
    "best_params": {
      "check_inverse": true,
      "func": null,
      "inverse_func": null,
      "regressor__bootstrap": true,
      "regressor__ccp_alpha": 0.0,
      "regressor__criterion": "squared_error",
      "regressor__max_depth": null,
      "regressor__max_features": "sqrt",
      "regressor__max_leaf_nodes": null,
      "regressor__max_samples": null,
      "regressor__min_impurity_decrease": 0.0,
      "regressor__min_samples_leaf": 0.05,
      "regressor__min_samples_split": 0.05,
      "regressor__min_weight_fraction_leaf": 0.0,
      "regressor__monotonic_cst": null,
      "regressor__n_estimators": 2000,
      "regressor__n_jobs": null,
      "regressor__oob_score": false,
      "regressor__random_state": null,
      "regressor__verbose": 0,
      "regressor__warm_start": false,
      "transformer__memory": null,
      "transformer__verbose": false,
      "transformer__y scaler__copy": true,
      "transformer__y scaler__with_mean": true,
      "transformer__y scaler__with_std": true
    }
  },
  "1234567890": {
    "fit_time": [
      0.06026625633239746,
      0.06078934669494629,
      0.054378509521484375,
      0.05082082748413086,
      0.060875892639160156
    ],
    "score_time": [
      0.011234045028686523,
      0.011005401611328125,
      0.011609315872192383,
      0.010860681533813477,
      0.010999441146850586
    ],
    "test_r": [
      0.4873946080244466,
      0.6474368036525582,
      0.5518644104486589,
      0.6598191234938909,
      0.6062743626463447
    ],
    "test_r2": [
      0.2354142626899236,
      0.29833984212997,
      0.2776914986420469,
      0.4210956242360624,
      0.3252064339109434
    ],
    "test_rmse": [
      -6.449673759673592,
      -7.875081522832382,
      -6.55784802464506,
      -4.962560265300162,
      -5.222349405334543
    ],
    "test_mae": [
      -3.5591594992976927,
      -4.178672126471877,
      -4.233625904189392,
      -3.550257336339513,
      -3.4181217708138836
    ],
    "best_params": {
      "check_inverse": true,
      "func": null,
      "inverse_func": null,
      "regressor__bootstrap": true,
      "regressor__ccp_alpha": 0.0,
      "regressor__criterion": "squared_error",
      "regressor__max_depth": null,
      "regressor__max_features": "sqrt",
      "regressor__max_leaf_nodes": null,
      "regressor__max_samples": null,
      "regressor__min_impurity_decrease": 0.0,
      "regressor__min_samples_leaf": 0.05128289077935,
      "regressor__min_samples_split": 0.08257725941344868,
      "regressor__min_weight_fraction_leaf": 0.0,
      "regressor__monotonic_cst": null,
      "regressor__n_estimators": 56,
      "regressor__n_jobs": null,
      "regressor__oob_score": false,
      "regressor__random_state": null,
      "regressor__verbose": 0,
      "regressor__warm_start": false,
      "transformer__memory": null,
      "transformer__verbose": false,
      "transformer__y scaler__copy": true,
      "transformer__y scaler__with_mean": true,
      "transformer__y scaler__with_std": true
    }
  },
  "473129": {
    "fit_time": [
      0.055910348892211914,
      0.05319619178771973,
      0.04725503921508789,
      0.04984116554260254,
      0.053281545639038086
    ],
    "score_time": [
      0.010432958602905273,
      0.01170206069946289,
      0.01058506965637207,
      0.01057291030883789,
      0.010686159133911133
    ],
    "test_r": [
      0.6724071896789817,
      0.6298295957187784,
      0.5621658488193387,
      0.7086953018217498,
      0.4701546623161252
    ],
    "test_r2": [
      0.3063066090027802,
      0.35844587742286294,
      0.3014479864961518,
      0.44014955487636453,
      0.20679565270167455
    ],
    "test_rmse": [
      -7.909866510907315,
      -4.3647919869893705,
      -6.956371136641133,
      -4.968576883218135,
      -5.962577527459917
    ],
    "test_mae": [
      -4.983207918713626,
      -3.1047018659283228,
      -3.7344091463388516,
      -3.442686717289788,
      -3.56159037210532
    ],
    "best_params": {
      "check_inverse": true,
      "func": null,
      "inverse_func": null,
      "regressor__bootstrap": true,
      "regressor__ccp_alpha": 0.0,
      "regressor__criterion": "squared_error",
      "regressor__max_depth": null,
      "regressor__max_features": "sqrt",
      "regressor__max_leaf_nodes": null,
      "regressor__max_samples": null,
      "regressor__min_impurity_decrease": 0.0,
      "regressor__min_samples_leaf": 0.05,
      "regressor__min_samples_split": 0.05,
      "regressor__min_weight_fraction_leaf": 0.0,
      "regressor__monotonic_cst": null,
      "regressor__n_estimators": 50,
      "regressor__n_jobs": null,
      "regressor__oob_score": false,
      "regressor__random_state": null,
      "regressor__verbose": 0,
      "regressor__warm_start": false,
      "transformer__memory": null,
      "transformer__verbose": false,
      "transformer__y scaler__copy": true,
      "transformer__y scaler__with_mean": true,
      "transformer__y scaler__with_std": true
    }
  },
  "r_avg": 0.6119114388579183,
  "r_stdev": 0.06694785639367666,
  "r2_avg": 0.3316613911061487,
  "r2_stdev": 0.07288635936382441,
  "rmse_avg": 6.107873841281099,
  "rmse_stdev": 1.2074966378141396,
  "mae_avg": 3.7992247894022357,
  "mae_stdev": 0.4956554862951611
}