{
  "6": {
    "fit_time": [
      1.1654667854309082,
      1.1153597831726074,
      1.1849794387817383,
      1.1652944087982178,
      1.149709939956665
    ],
    "score_time": [
      0.20679950714111328,
      0.2292311191558838,
      0.21204352378845215,
      0.21465682983398438,
      0.21632909774780273
    ],
    "test_r": [
      0.9939873247245716,
      0.9887368289501534,
      0.3994638260282249,
      0.9967498267559332,
      0.9599343302991378
    ],
    "test_r2": [
      0.9623987078666687,
      0.9727506637573242,
      -1.9343383312225342,
      0.9731831550598145,
      0.9137893915176392
    ],
    "test_rmse": [
      -32.007117056558876,
      -19.75835017798102,
      -105.54118862958629,
      -22.562534120995924,
      -20.43240828438484
    ],
    "test_mae": [
      -16.08765421514658,
      -12.27587004342886,
      -22.984993089420094,
      -11.548005829455807,
      -13.181617764838723
    ],
    "best_params": {
      "check_inverse": true,
      "func": null,
      "inverse_func": null,
      "regressor__objective": "reg:squarederror",
      "regressor__base_score": null,
      "regressor__booster": null,
      "regressor__callbacks": null,
      "regressor__colsample_bylevel": null,
      "regressor__colsample_bynode": null,
      "regressor__colsample_bytree": null,
      "regressor__device": null,
      "regressor__early_stopping_rounds": null,
      "regressor__enable_categorical": false,
      "regressor__eval_metric": null,
      "regressor__feature_types": null,
      "regressor__gamma": null,
      "regressor__grow_policy": null,
      "regressor__importance_type": null,
      "regressor__interaction_constraints": null,
      "regressor__learning_rate": 0.014630650415646108,
      "regressor__max_bin": null,
      "regressor__max_cat_threshold": null,
      "regressor__max_cat_to_onehot": null,
      "regressor__max_delta_step": null,
      "regressor__max_depth": 36,
      "regressor__max_leaves": null,
      "regressor__min_child_weight": null,
      "regressor__missing": NaN,
      "regressor__monotone_constraints": null,
      "regressor__multi_strategy": null,
      "regressor__n_estimators": 193,
      "regressor__n_jobs": -2,
      "regressor__num_parallel_tree": null,
      "regressor__random_state": null,
      "regressor__reg_alpha": null,
      "regressor__reg_lambda": null,
      "regressor__sampling_method": null,
      "regressor__scale_pos_weight": null,
      "regressor__subsample": null,
      "regressor__tree_method": null,
      "regressor__validate_parameters": null,
      "regressor__verbosity": null,
      "transformer__memory": null,
      "transformer__verbose": false,
      "transformer__y scaler__copy": true,
      "transformer__y scaler__with_mean": true,
      "transformer__y scaler__with_std": true
    }
  },
  "13": {
    "fit_time": [
      8.67650318145752,
      8.664266586303711,
      8.76274585723877,
      8.614696025848389,
      8.785278797149658
    ],
    "score_time": [
      0.2123572826385498,
      0.21189045906066895,
      0.2142634391784668,
      0.21987485885620117,
      0.2627701759338379
    ],
    "test_r": [
      0.9689595011720564,
      0.7497987833450857,
      0.9875424596973571,
      0.9876565977758707,
      0.9739939602414021
    ],
    "test_r2": [
      0.8943679332733154,
      0.5199631452560425,
      0.9526962041854858,
      0.9650650024414062,
      0.931955099105835
    ],
    "test_rmse": [
      -16.252852678596074,
      -101.75800037993697,
      -34.21329334327426,
      -22.926800484130776,
      -20.047714420116588
    ],
    "test_mae": [
      -11.514934936077411,
      -32.1035799992488,
      -17.807667859844134,
      -13.237506457902494,
      -14.295086592042216
    ],
    "best_params": {
      "check_inverse": true,
      "func": null,
      "inverse_func": null,
      "regressor__objective": "reg:squarederror",
      "regressor__base_score": null,
      "regressor__booster": null,
      "regressor__callbacks": null,
      "regressor__colsample_bylevel": null,
      "regressor__colsample_bynode": null,
      "regressor__colsample_bytree": null,
      "regressor__device": null,
      "regressor__early_stopping_rounds": null,
      "regressor__enable_categorical": false,
      "regressor__eval_metric": null,
      "regressor__feature_types": null,
      "regressor__gamma": null,
      "regressor__grow_policy": null,
      "regressor__importance_type": null,
      "regressor__interaction_constraints": null,
      "regressor__learning_rate": 0.0011974730150601694,
      "regressor__max_bin": null,
      "regressor__max_cat_threshold": null,
      "regressor__max_cat_to_onehot": null,
      "regressor__max_delta_step": null,
      "regressor__max_depth": 10,
      "regressor__max_leaves": null,
      "regressor__min_child_weight": null,
      "regressor__missing": NaN,
      "regressor__monotone_constraints": null,
      "regressor__multi_strategy": null,
      "regressor__n_estimators": 2000,
      "regressor__n_jobs": -2,
      "regressor__num_parallel_tree": null,
      "regressor__random_state": null,
      "regressor__reg_alpha": null,
      "regressor__reg_lambda": null,
      "regressor__sampling_method": null,
      "regressor__scale_pos_weight": null,
      "regressor__subsample": null,
      "regressor__tree_method": null,
      "regressor__validate_parameters": null,
      "regressor__verbosity": null,
      "transformer__memory": null,
      "transformer__verbose": false,
      "transformer__y scaler__copy": true,
      "transformer__y scaler__with_mean": true,
      "transformer__y scaler__with_std": true
    }
  },
  "42": {
    "fit_time": [
      0.4859619140625,
      0.5024023056030273,
      0.5021631717681885,
      0.5136585235595703,
      0.5089523792266846
    ],
    "score_time": [
      0.20462894439697266,
      0.21283555030822754,
      0.2090754508972168,
      0.20881032943725586,
      0.20850276947021484
    ],
    "test_r": [
      0.9886962583530933,
      0.9727874891918407,
      0.8068060826538845,
      0.9895453826732779,
      0.9892067287422106
    ],
    "test_r2": [
      0.9712855219841003,
      0.9408664703369141,
      0.6103178262710571,
      0.9781469106674194,
      0.9782288670539856
    ],
    "test_rmse": [
      -20.37010716316429,
      -18.07026282723199,
      -107.41656239525592,
      -19.408382860644537,
      -9.365005382394651
    ],
    "test_mae": [
      -12.863569789992113,
      -10.835067280845639,
      -30.315463538094313,
      -11.392507453732955,
      -6.2985735697488225
    ],
    "best_params": {
      "check_inverse": true,
      "func": null,
      "inverse_func": null,
      "regressor__objective": "reg:squarederror",
      "regressor__base_score": null,
      "regressor__booster": null,
      "regressor__callbacks": null,
      "regressor__colsample_bylevel": null,
      "regressor__colsample_bynode": null,
      "regressor__colsample_bytree": null,
      "regressor__device": null,
      "regressor__early_stopping_rounds": null,
      "regressor__enable_categorical": false,
      "regressor__eval_metric": null,
      "regressor__feature_types": null,
      "regressor__gamma": null,
      "regressor__grow_policy": null,
      "regressor__importance_type": null,
      "regressor__interaction_constraints": null,
      "regressor__learning_rate": 0.07416997954503883,
      "regressor__max_bin": null,
      "regressor__max_cat_threshold": null,
      "regressor__max_cat_to_onehot": null,
      "regressor__max_delta_step": null,
      "regressor__max_depth": 10000,
      "regressor__max_leaves": null,
      "regressor__min_child_weight": null,
      "regressor__missing": NaN,
      "regressor__monotone_constraints": null,
      "regressor__multi_strategy": null,
      "regressor__n_estimators": 50,
      "regressor__n_jobs": -2,
      "regressor__num_parallel_tree": null,
      "regressor__random_state": null,
      "regressor__reg_alpha": null,
      "regressor__reg_lambda": null,
      "regressor__sampling_method": null,
      "regressor__scale_pos_weight": null,
      "regressor__subsample": null,
      "regressor__tree_method": null,
      "regressor__validate_parameters": null,
      "regressor__verbosity": null,
      "transformer__memory": null,
      "transformer__verbose": false,
      "transformer__y scaler__copy": true,
      "transformer__y scaler__with_mean": true,
      "transformer__y scaler__with_std": true
    }
  },
  "69": {
    "fit_time": [
      2.7835800647735596,
      2.744377851486206,
      2.7409369945526123,
      2.7476329803466797,
      2.690239667892456
    ],
    "score_time": [
      0.2598121166229248,
      0.26186656951904297,
      0.26389336585998535,
      0.2638568878173828,
      0.25305652618408203
    ],
    "test_r": [
      0.9970715421062103,
      0.6789863964667158,
      0.9768940066172247,
      0.9713669946448059,
      0.9939053658532742
    ],
    "test_r2": [
      0.985445499420166,
      -0.23401904106140137,
      0.9450733661651611,
      0.9403454661369324,
      0.9869639873504639
    ],
    "test_rmse": [
      -16.595650089564245,
      -174.09703525093838,
      -14.607636871034009,
      -16.53365494064343,
      -15.330066748714298
    ],
    "test_mae": [
      -7.77357309713804,
      -46.87908677652505,
      -7.400322326950374,
      -8.771852652716543,
      -9.576851587687473
    ],
    "best_params": {
      "check_inverse": true,
      "func": null,
      "inverse_func": null,
      "regressor__objective": "reg:squarederror",
      "regressor__base_score": null,
      "regressor__booster": null,
      "regressor__callbacks": null,
      "regressor__colsample_bylevel": null,
      "regressor__colsample_bynode": null,
      "regressor__colsample_bytree": null,
      "regressor__device": null,
      "regressor__early_stopping_rounds": null,
      "regressor__enable_categorical": false,
      "regressor__eval_metric": null,
      "regressor__feature_types": null,
      "regressor__gamma": null,
      "regressor__grow_policy": null,
      "regressor__importance_type": null,
      "regressor__interaction_constraints": null,
      "regressor__learning_rate": 0.06749707438850708,
      "regressor__max_bin": null,
      "regressor__max_cat_threshold": null,
      "regressor__max_cat_to_onehot": null,
      "regressor__max_delta_step": null,
      "regressor__max_depth": 468,
      "regressor__max_leaves": null,
      "regressor__min_child_weight": null,
      "regressor__missing": NaN,
      "regressor__monotone_constraints": null,
      "regressor__multi_strategy": null,
      "regressor__n_estimators": 1230,
      "regressor__n_jobs": -2,
      "regressor__num_parallel_tree": null,
      "regressor__random_state": null,
      "regressor__reg_alpha": null,
      "regressor__reg_lambda": null,
      "regressor__sampling_method": null,
      "regressor__scale_pos_weight": null,
      "regressor__subsample": null,
      "regressor__tree_method": null,
      "regressor__validate_parameters": null,
      "regressor__verbosity": null,
      "transformer__memory": null,
      "transformer__verbose": false,
      "transformer__y scaler__copy": true,
      "transformer__y scaler__with_mean": true,
      "transformer__y scaler__with_std": true
    }
  },
  "420": {
    "fit_time": [
      1.0959346294403076,
      1.134247064590454,
      1.0985615253448486,
      1.1312429904937744,
      1.157641887664795
    ],
    "score_time": [
      0.2035837173461914,
      0.1990499496459961,
      0.2068772315979004,
      0.20267438888549805,
      0.20394563674926758
    ],
    "test_r": [
      0.9900749164629512,
      0.9932117046639601,
      0.7260778324590189,
      0.9761839505801166,
      0.9956222834829621
    ],
    "test_r2": [
      0.9717252850532532,
      0.9788004755973816,
      0.4268454909324646,
      0.9380978345870972,
      0.9664677381515503
    ],
    "test_rmse": [
      -11.494349607895717,
      -23.25671109091309,
      -104.32535372207623,
      -18.700691130811716,
      -23.147658943497156
    ],
    "test_mae": [
      -8.262949741885844,
      -14.935807275789703,
      -31.004550674773572,
      -12.58500562336641,
      -12.378070649701288
    ],
    "best_params": {
      "check_inverse": true,
      "func": null,
      "inverse_func": null,
      "regressor__objective": "reg:squarederror",
      "regressor__base_score": null,
      "regressor__booster": null,
      "regressor__callbacks": null,
      "regressor__colsample_bylevel": null,
      "regressor__colsample_bynode": null,
      "regressor__colsample_bytree": null,
      "regressor__device": null,
      "regressor__early_stopping_rounds": null,
      "regressor__enable_categorical": false,
      "regressor__eval_metric": null,
      "regressor__feature_types": null,
      "regressor__gamma": null,
      "regressor__grow_policy": null,
      "regressor__importance_type": null,
      "regressor__interaction_constraints": null,
      "regressor__learning_rate": 0.013351464778181547,
      "regressor__max_bin": null,
      "regressor__max_cat_threshold": null,
      "regressor__max_cat_to_onehot": null,
      "regressor__max_delta_step": null,
      "regressor__max_depth": 943,
      "regressor__max_leaves": null,
      "regressor__min_child_weight": null,
      "regressor__missing": NaN,
      "regressor__monotone_constraints": null,
      "regressor__multi_strategy": null,
      "regressor__n_estimators": 197,
      "regressor__n_jobs": -2,
      "regressor__num_parallel_tree": null,
      "regressor__random_state": null,
      "regressor__reg_alpha": null,
      "regressor__reg_lambda": null,
      "regressor__sampling_method": null,
      "regressor__scale_pos_weight": null,
      "regressor__subsample": null,
      "regressor__tree_method": null,
      "regressor__validate_parameters": null,
      "regressor__verbosity": null,
      "transformer__memory": null,
      "transformer__verbose": false,
      "transformer__y scaler__copy": true,
      "transformer__y scaler__with_mean": true,
      "transformer__y scaler__with_std": true
    }
  },
  "1234567890": {
    "fit_time": [
      0.4636504650115967,
      0.48386478424072266,
      0.45686793327331543,
      0.47054243087768555,
      0.46877193450927734
    ],
    "score_time": [
      0.19978928565979004,
      0.20425081253051758,
      0.2014024257659912,
      0.20015645027160645,
      0.20044517517089844
    ],
    "test_r": [
      0.9612394375571482,
      0.9880606804963236,
      0.9943835348750151,
      0.9954008652364204,
      0.6640577887277397
    ],
    "test_r2": [
      0.922295331954956,
      0.9685692191123962,
      0.9849987626075745,
      0.9547911286354065,
      0.27212321758270264
    ],
    "test_rmse": [
      -18.713372804214504,
      -22.233472508362308,
      -15.21457064700193,
      -29.135771054594482,
      -111.90037861300726
    ],
    "test_mae": [
      -10.317223000218316,
      -13.299791840133667,
      -10.8014129249483,
      -12.42216390604655,
      -37.43572627685546
    ],
    "best_params": {
      "check_inverse": true,
      "func": null,
      "inverse_func": null,
      "regressor__objective": "reg:squarederror",
      "regressor__base_score": null,
      "regressor__booster": null,
      "regressor__callbacks": null,
      "regressor__colsample_bylevel": null,
      "regressor__colsample_bynode": null,
      "regressor__colsample_bytree": null,
      "regressor__device": null,
      "regressor__early_stopping_rounds": null,
      "regressor__enable_categorical": false,
      "regressor__eval_metric": null,
      "regressor__feature_types": null,
      "regressor__gamma": null,
      "regressor__grow_policy": null,
      "regressor__importance_type": null,
      "regressor__interaction_constraints": null,
      "regressor__learning_rate": 0.052750195344906416,
      "regressor__max_bin": null,
      "regressor__max_cat_threshold": null,
      "regressor__max_cat_to_onehot": null,
      "regressor__max_delta_step": null,
      "regressor__max_depth": 10000,
      "regressor__max_leaves": null,
      "regressor__min_child_weight": null,
      "regressor__missing": NaN,
      "regressor__monotone_constraints": null,
      "regressor__multi_strategy": null,
      "regressor__n_estimators": 50,
      "regressor__n_jobs": -2,
      "regressor__num_parallel_tree": null,
      "regressor__random_state": null,
      "regressor__reg_alpha": null,
      "regressor__reg_lambda": null,
      "regressor__sampling_method": null,
      "regressor__scale_pos_weight": null,
      "regressor__subsample": null,
      "regressor__tree_method": null,
      "regressor__validate_parameters": null,
      "regressor__verbosity": null,
      "transformer__memory": null,
      "transformer__verbose": false,
      "transformer__y scaler__copy": true,
      "transformer__y scaler__with_mean": true,
      "transformer__y scaler__with_std": true
    }
  },
  "473129": {
    "fit_time": [
      0.7444605827331543,
      0.7567591667175293,
      0.7363126277923584,
      0.7616369724273682,
      0.7595932483673096
    ],
    "score_time": [
      0.2039949893951416,
      0.20908212661743164,
      0.2073957920074463,
      0.2024674415588379,
      0.20474505424499512
    ],
    "test_r": [
      0.9951014673260277,
      0.7319978328470793,
      0.992063479694957,
      0.9676006329703034,
      0.96793055595206
    ],
    "test_r2": [
      0.9649173021316528,
      0.3555557131767273,
      0.9839965105056763,
      0.9276434183120728,
      0.9317901730537415
    ],
    "test_rmse": [
      -23.418655745460722,
      -106.5889995716806,
      -19.789546604047583,
      -22.460120367933516,
      -20.21680956071069
    ],
    "test_mae": [
      -9.802431204822247,
      -25.008318577305715,
      -12.264542203716202,
      -12.356332910204118,
      -11.489514638668881
    ],
    "best_params": {
      "check_inverse": true,
      "func": null,
      "inverse_func": null,
      "regressor__objective": "reg:squarederror",
      "regressor__base_score": null,
      "regressor__booster": null,
      "regressor__callbacks": null,
      "regressor__colsample_bylevel": null,
      "regressor__colsample_bynode": null,
      "regressor__colsample_bytree": null,
      "regressor__device": null,
      "regressor__early_stopping_rounds": null,
      "regressor__enable_categorical": false,
      "regressor__eval_metric": null,
      "regressor__feature_types": null,
      "regressor__gamma": null,
      "regressor__grow_policy": null,
      "regressor__importance_type": null,
      "regressor__interaction_constraints": null,
      "regressor__learning_rate": 0.02873163707732401,
      "regressor__max_bin": null,
      "regressor__max_cat_threshold": null,
      "regressor__max_cat_to_onehot": null,
      "regressor__max_delta_step": null,
      "regressor__max_depth": 10,
      "regressor__max_leaves": null,
      "regressor__min_child_weight": null,
      "regressor__missing": NaN,
      "regressor__monotone_constraints": null,
      "regressor__multi_strategy": null,
      "regressor__n_estimators": 114,
      "regressor__n_jobs": -2,
      "regressor__num_parallel_tree": null,
      "regressor__random_state": null,
      "regressor__reg_alpha": null,
      "regressor__reg_lambda": null,
      "regressor__sampling_method": null,
      "regressor__scale_pos_weight": null,
      "regressor__subsample": null,
      "regressor__tree_method": null,
      "regressor__validate_parameters": null,
      "regressor__verbosity": null,
      "transformer__memory": null,
      "transformer__verbose": false,
      "transformer__y scaler__copy": true,
      "transformer__y scaler__with_mean": true,
      "transformer__y scaler__with_std": true
    }
  },
  "r_avg": 0.9231741899892688,
  "r_stdev": 0.1339050798520342,
  "r2_avg": 0.7658029556274414,
  "r2_stdev": 0.5328634635131799,
  "rmse_avg": 39.368316745067276,
  "rmse_stdev": 40.03802053895353,
  "mae_avg": 15.75736075169351,
  "mae_stdev": 9.17139412796964
}